dsnparse3.py
dsnparse3-0.1.3.dist-info/DESCRIPTION.rst
dsnparse3-0.1.3.dist-info/METADATA
dsnparse3-0.1.3.dist-info/metadata.json
dsnparse3-0.1.3.dist-info/RECORD
dsnparse3-0.1.3.dist-info/top_level.txt
dsnparse3-0.1.3.dist-info/WHEEL
