Metadata-Version: 2.0
Name: dsnparse3
Version: 0.1.3
Summary: parse dsn urls
Home-page: http://github.com/mylokin/dsnparse3
Author: Jay Marcyes
Author-email: jay@marcyes.com
License: MIT
Platform: UNKNOWN
Classifier: Development Status :: 4 - Beta
Classifier: Environment :: Plugins
Classifier: Intended Audience :: Developers
Classifier: License :: OSI Approved :: MIT License
Classifier: Operating System :: OS Independent
Classifier: Programming Language :: Python :: 3.4
